Workbook

Sheet Cobros 3D
M1: =SUMIF(M3:M131, ">0") -> 213600 | N1: =SUMIF(N3:N131, ">0") -> 121923.51
A2: Solicitante | B2: Marca temporal | C2: Descripcion del proyecto | D2: Material | E2: Color principal | F2: Gramos | G2: Duracion de la impresion | H2: Diseño | I2: precio por material | J2: precio por tiempo | K2: Tipo de proyecto | L2: Descuento | M2: Precio | N2: Costo total | O2: Costo de material | P2: Costo de tiempo | Q2: Pago inicial | R2: Pago final
A3: Edward Velasco | B3: 46138.504 | C3: Rockie | D3: PLA | E3: Negro | F3: 24.46 | G3: 0.17916667 | H3: 0 | I3: {=IF(D3=0,0,XLOOKUP(D3,Costos!$B$3:$B131,Costos!$G$3:$G131)*F3)} -> 4402.8 | J3: =G3*(Costos!$I$2+Costos!$I$3)*24 -> 5160 | K3: Cúmulo VIP | L3: =IF(K3="Cúmulo VIP",Costos!$I$4,0) -> 0.2 | M3: =IF(K3="Proyecto Cúmulo",0,MROUND(SUM(I3:J3)*(1-L3), 100)) -> 7700 | N3: =O3+P3 -> 2958.668 | O3: {=F3*XLOOKUP(D3,Costos!$B:$B,Costos!$E:$E)} -> 2098.668 | P3: =G3*24*Costos!$I$3 -> 860
A4: Diego Bernal | B4: 46138.516 | C4: Spaceman | D4: PLA | E4: Negro | F4: 12.54 | G4: 0.19305556 | H4: 0 | I4: {=IF(D4=0,0,XLOOKUP(D4,Costos!$B$3:$B131,Costos!$G$3:$G131)*F4)} -> 2257.2 | J4: =G4*(Costos!$I$2+Costos!$I$3)*24 -> 5560 | K4: Cúmulo VIP | L4: =IF(K4="Cúmulo VIP",Costos!$I$4,0) -> 0.2 | M4: =IF(K4="Proyecto Cúmulo",0,MROUND(SUM(I4:J4)*(1-L4), 100)) -> 6300 | N4: =O4+P4 -> 2002.5987 | O4: {=F4*XLOOKUP(D4,Costos!$B:$B,Costos!$E:$E)} -> 1075.932 | P4: =G4*24*Costos!$I$3 -> 926.66667 | R4: 5500
A5: Jesus Steven Ospina | B5: 46138.52 | C5: Soporte para micrófono | D5: PLA glow | E5: Verde | F5: 26 | G5: 0.041666667 | H5: 0 | I5: {=IF(D5=0,0,XLOOKUP(D5,Costos!$B$3:$B131,Costos!$G$3:$G131)*F5)} -> 5200 | J5: =G5*(Costos!$I$2+Costos!$I$3)*24 -> 1200 | K5: Cúmulo VIP | L5: =IF(K5="Cúmulo VIP",Costos!$I$4,0) -> 0.2 | M5: =IF(K5="Proyecto Cúmulo",0,MROUND(SUM(I5:J5)*(1-L5), 100)) -> 5100 | N5: =O5+P5 -> 2843.3333 | O5: {=F5*XLOOKUP(D5,Costos!$B:$B,Costos!$E:$E)} -> 2643.3333 | P5: =G5*24*Costos!$I$3 -> 200 | R5: 4500
A6: Diego Forero | B6: 46138.524 | C6: Pata de bandeja | D6: ABS | E6: Gris | F6: 18 | G6: 0.020833333 | H6: 0 | I6: {=IF(D6=0,0,XLOOKUP(D6,Costos!$B$3:$B131,Costos!$G$3:$G131)*F6)} -> 3780 | J6: =G6*(Costos!$I$2+Costos!$I$3)*24 -> 600 | K6: Tercero | L6: =IF(K6="Cúmulo VIP",Costos!$I$4,0) -> 0 | M6: =IF(K6="Proyecto Cúmulo",0,MROUND(SUM(I6:J6)*(1-L6), 100)) -> 4400 | N6: =O6+P6 -> 1554.4 | O6: {=F6*XLOOKUP(D6,Costos!$B:$B,Costos!$E:$E)} -> 1454.4 | P6: =G6*24*Costos!$I$3 -> 100 | R6: 2500
A7: Nicolle Arévalo | B7: 46138.526 | C7: Fliptext | D7: PLA | E7: Negro | F7: 18.8 | G7: 0.0625 | H7: 0 | I7: {=IF(D7=0,0,XLOOKUP(D7,Costos!$B$3:$B131,Costos!$G$3:$G131)*F7)} -> 3384 | J7: =G7*(Costos!$I$2+Costos!$I$3)*24 -> 1800 | K7: Cúmulo VIP | L7: =IF(K7="Cúmulo VIP",Costos!$I$4,0) -> 0.2 | M7: =IF(K7="Proyecto Cúmulo",0,MROUND(SUM(I7:J7)*(1-L7), 100)) -> 4100 | N7: =O7+P7 -> 1913.04 | O7: {=F7*XLOOKUP(D7,Costos!$B:$B,Costos!$E:$E)} -> 1613.04 | P7: =G7*24*Costos!$I$3 -> 300 | R7: 4600
A8: Felipe Muñoz | B8: 46138.529 | C8: Caja de maquinilla | D8: PLA | E8: Blanco | F8: 0 | G8: 0.10416667 | H8: 0 | I8: {=IF(D8=0,0,XLOOKUP(D8,Costos!$B$3:$B131,Costos!$G$3:$G131)*F8)} -> 0 | J8: =G8*(Costos!$I$2+Costos!$I$3)*24 -> 3000 | K8: Cúmulo VIP | L8: =IF(K8="Cúmulo VIP",Costos!$I$4,0) -> 0.2 | M8: =IF(K8="Proyecto Cúmulo",0,MROUND(SUM(I8:J8)*(1-L8), 100)) -> 2400 | N8: =O8+P8 -> 500 | O8: {=F8*XLOOKUP(D8,Costos!$B:$B,Costos!$E:$E)} -> 0 | P8: =G8*24*Costos!$I$3 -> 500 | R8: 5000
A9: Daniel Felipe Garnica | B9: 46138.533 | C9: Araña | D9: PLA | E9: Blanco | F9: 43.5 | G9: 0.083333333 | H9: 0 | I9: {=IF(D9=0,0,XLOOKUP(D9,Costos!$B$3:$B131,Costos!$G$3:$G131)*F9)} -> 7830 | J9: =G9*(Costos!$I$2+Costos!$I$3)*24 -> 2400 | K9: Cúmulo VIP | L9: =IF(K9="Cúmulo VIP",Costos!$I$4,0) -> 0.2 | M9: =IF(K9="Proyecto Cúmulo",0,MROUND(SUM(I9:J9)*(1-L9), 100)) -> 8200 | N9: =O9+P9 -> 4132.3 | O9: {=F9*XLOOKUP(D9,Costos!$B:$B,Costos!$E:$E)} -> 3732.3 | P9: =G9*24*Costos!$I$3 -> 400 | R9: 5700
A10: Santiago Fonseca | B10: 46138.536 | C10: Cubierta de vaso | D10: PLA | E10: Negro | F10: 17 | G10: 0.027777778 | H10: 0 | I10: {=IF(D10=0,0,XLOOKUP(D10,Costos!$B$3:$B131,Costos!$G$3:$G131)*F10)} -> 3060 | J10: =G10*(Costos!$I$2+Costos!$I$3)*24 -> 800 | K10: Tercero | L10: =IF(K10="Cúmulo VIP",Costos!$I$4,0) -> 0 | M10: =IF(K10="Proyecto Cúmulo",0,MROUND(SUM(I10:J10)*(1-L10), 100)) -> 3900 | N10: =O10+P10 -> 1591.9333 | O10: {=F10*XLOOKUP(D10,Costos!$B:$B,Costos!$E:$E)} -> 1458.6 | P10: =G10*24*Costos!$I$3 -> 133.33333 | R10: 0
A11: Cúmulo | B11: 46138.541 | C11: Código QR de Cúmulo | D11: PLA | E11: Negro | F11: 70.5 | H11: 0 | I11: {=IF(D11=0,0,XLOOKUP(D11,Costos!$B$3:$B$6,Costos!$G$3:$G$6)*F11)} -> 12690 | J11: =G11*(Costos!$I$2+Costos!$I$3)*24 -> 0 | K11: Proyecto Cúmulo | L11: =IF(K11="Cúmulo VIP",Costos!$I$4,0) -> 0 | M11: =IF(K11="Proyecto Cúmulo",0,MROUND(SUM(I11:J11)*(1-L11), 100)) -> 0 | N11: =O11+P11 -> 6048.9 | O11: {=F11*XLOOKUP(D11,Costos!$B:$B,Costos!$E:$E)} -> 6048.9 | P11: =G11*24*Costos!$I$3 -> 0
A12: Cúmulo | B12: 46138.543 | C12: Plantilla para graffiti logo de Cúmulo | D12: PLA | E12: Negro | F12: 84.9 | H12: 0 | I12: {=IF(D12=0,0,XLOOKUP(D12,Costos!$B$3:$B$6,Costos!$G$3:$G$6)*F12)} -> 15282 | J12: =G12*(Costos!$I$2+Costos!$I$3)*24 -> 0 | K12: Proyecto Cúmulo | L12: =IF(K12="Cúmulo VIP",Costos!$I$4,0) -> 0 | M12: =IF(K12="Proyecto Cúmulo",0,MROUND(SUM(I12:J12)*(1-L12), 100)) -> 0 | N12: =O12+P12 -> 7284.42 | O12: {=F12*XLOOKUP(D12,Costos!$B:$B,Costos!$E:$E)} -> 7284.42 | P12: =G12*24*Costos!$I$3 -> 0
A13: Cúmulo | B13: 46138.544 | C13: Medidor de tornillos | D13: PLA | E13: Negro | F13: 5.3 | H13: 0 | I13: {=IF(D13=0,0,XLOOKUP(D13,Costos!$B$3:$B$6,Costos!$G$3:$G$6)*F13)} -> 954 | J13: =G13*(Costos!$I$2+Costos!$I$3)*24 -> 0 | K13: Proyecto Cúmulo | L13: =IF(K13="Cúmulo VIP",Costos!$I$4,0) -> 0 | M13: =IF(K13="Proyecto Cúmulo",0,MROUND(SUM(I13:J13)*(1-L13), 100)) -> 0 | N13: =O13+P13 -> 454.74 | O13: {=F13*XLOOKUP(D13,Costos!$B:$B,Costos!$E:$E)} -> 454.74 | P13: =G13*24*Costos!$I$3 -> 0
A14: Cúmulo | B14: 46138.545 | C14: Esquina puerta de la impresora | D14: PLA | E14: Negro | F14: 15.3 | H14: 0 | I14: {=IF(D14=0,0,XLOOKUP(D14,Costos!$B$3:$B$6,Costos!$G$3:$G$6)*F14)} -> 2754 | J14: =G14*(Costos!$I$2+Costos!$I$3)*24 -> 0 | K14: Proyecto Cúmulo | L14: =IF(K14="Cúmulo VIP",Costos!$I$4,0) -> 0 | M14: =IF(K14="Proyecto Cúmulo",0,MROUND(SUM(I14:J14)*(1-L14), 100)) -> 0 | N14: =O14+P14 -> 1312.74 | O14: {=F14*XLOOKUP(D14,Costos!$B:$B,Costos!$E:$E)} -> 1312.74 | P14: =G14*24*Costos!$I$3 -> 0
A15: Cúmulo | B15: 46138.56 | C15: Benchy de tpu | D15: TPU 95a | E15: Translúcido | F15: 9.8 | H15: 0 | I15: {=IF(D15=0,0,XLOOKUP(D15,Costos!$B$3:$B$6,Costos!$G$3:$G$6)*F15)} -> 1960 | J15: =G15*(Costos!$I$2+Costos!$I$3)*24 -> 0 | K15: Proyecto Cúmulo | L15: =IF(K15="Cúmulo VIP",Costos!$I$4,0) -> 0 | M15: =IF(K15="Proyecto Cúmulo",0,MROUND(SUM(I15:J15)*(1-L15), 100)) -> 0 | N15: =O15+P15 -> 889.84 | O15: {=F15*XLOOKUP(D15,Costos!$B:$B,Costos!$E:$E)} -> 889.84 | P15: =G15*24*Costos!$I$3 -> 0
A16: Sebastián Lozano | B16: 46138.585 | C16: Impresión desconocida | D16: PLA | E16: Negro | F16: 0 | G16: 0.10416667 | H16: 0 | I16: {=IF(D16=0,0,XLOOKUP(D16,Costos!$B$3:$B131,Costos!$G$3:$G131)*F16)} -> 0 | J16: =G16*(Costos!$I$2+Costos!$I$3)*24 -> 3000 | K16: Cúmulo VIP | L16: =IF(K16="Cúmulo VIP",Costos!$I$4,0) -> 0.2 | M16: =IF(K16="Proyecto Cúmulo",0,MROUND(SUM(I16:J16)*(1-L16), 100)) -> 2400 | N16: =O16+P16 -> 500 | O16: {=F16*XLOOKUP(D16,Costos!$B:$B,Costos!$E:$E)} -> 0 | P16: =G16*24*Costos!$I$3 -> 500 | R16: 4000
A17: Yeimy Telles | B17: 46142.792 | C17: Rockie de Project Hail Mary | D17: PLA glow | E17: Verde | F17: 37 | G17: 0.20833333 | H17: 0 | I17: {=IF(D17=0,0,XLOOKUP(D17,Costos!$B$3:$B131,Costos!$G$3:$G131)*F17)} -> 7400 | J17: =G17*(Costos!$I$2+Costos!$I$3)*24 -> 6000 | K17: Cúmulo VIP | L17: =IF(K17="Cúmulo VIP",Costos!$I$4,0) -> 0.2 | M17: =IF(K17="Proyecto Cúmulo",0,MROUND(SUM(I17:J17)*(1-L17), 100)) -> 10700 | N17: =O17+P17 -> 4761.6667 | O17: {=F17*XLOOKUP(D17,Costos!$B:$B,Costos!$E:$E)} -> 3761.6667 | P17: =G17*24*Costos!$I$3 -> 1000 | R17: 7700
A18: Astrochaza | B18: 46142.794 | C18: Figuras del espacio | D18: PLA glow | E18: Verde | F18: 103.44 | H18: 0 | I18: {=IF(D18=0,0,XLOOKUP(D18,Costos!$B$3:$B131,Costos!$G$3:$G131)*F18)} -> 20688 | J18: =G18*(Costos!$I$2+Costos!$I$3)*24 -> 0 | K18: Astrochaza | L18: =IF(K18="Cúmulo VIP",Costos!$I$4,0) -> 0 | M18: =IF(K18="Proyecto Cúmulo",0,MROUND(SUM(I18:J18)*(1-L18), 100)) -> 20700 | N18: =O18+P18 -> 10516.4 | O18: {=F18*XLOOKUP(D18,Costos!$B:$B,Costos!$E:$E)} -> 10516.4 | P18: =G18*24*Costos!$I$3 -> 0
A19: Astrochaza | B19: 46142.804 | C19: Estrellitas | D19: PLA glow | E19: Verde | F19: 63.7 | H19: 0 | I19: {=IF(D19=0,0,XLOOKUP(D19,Costos!$B$3:$B131,Costos!$G$3:$G131)*F19)} -> 12740 | J19: =G19*(Costos!$I$2+Costos!$I$3)*24 -> 0 | K19: Astrochaza | L19: =IF(K19="Cúmulo VIP",Costos!$I$4,0) -> 0 | M19: =IF(K19="Proyecto Cúmulo",0,MROUND(SUM(I19:J19)*(1-L19), 100)) -> 12700 | N19: =O19+P19 -> 6476.1667 | O19: {=F19*XLOOKUP(D19,Costos!$B:$B,Costos!$E:$E)} -> 6476.1667 | P19: =G19*24*Costos!$I$3 -> 0
A20: Cúmulo | B20: 46142.805 | C20: Esquina impresora | D20: PLA | E20: Negro | F20: 9.1 | H20: 0 | I20: {=IF(D20=0,0,XLOOKUP(D20,Costos!$B$3:$B$6,Costos!$G$3:$G$6)*F20)} -> 1638 | J20: =G20*(Costos!$I$2+Costos!$I$3)*24 -> 0 | K20: Proyecto Cúmulo | L20: =IF(K20="Cúmulo VIP",Costos!$I$4,0) -> 0 | M20: =IF(K20="Proyecto Cúmulo",0,MROUND(SUM(I20:J20)*(1-L20), 100)) -> 0 | N20: =O20+P20 -> 780.78 | O20: {=F20*XLOOKUP(D20,Costos!$B:$B,Costos!$E:$E)} -> 780.78 | P20: =G20*24*Costos!$I$3 -> 0
A21: Astrochaza | B21: 46142.848 | C21: Estrellitas y astronauta | D21: PLA glow | E21: Verde | F21: 43.6 | H21: 0 | I21: {=IF(D21=0,0,XLOOKUP(D21,Costos!$B$3:$B131,Costos!$G$3:$G131)*F21)} -> 8720 | J21: =G21*(Costos!$I$2+Costos!$I$3)*24 -> 0 | K21: Astrochaza | L21: =IF(K21="Cúmulo VIP",Costos!$I$4,0) -> 0 | M21: 8300 | N21: =O21+P21 -> 4432.6667 | O21: {=F21*XLOOKUP(D21,Costos!$B:$B,Costos!$E:$E)} -> 4432.6667 | P21: =G21*24*Costos!$I$3 -> 0
A22: Cúmulo | B22: 46144.783 | C22: Benchy de abs | D22: ABS | E22: Gris | F22: 8 | I22: {=IF(D22=0,0,XLOOKUP(D22,Costos!$B$3:$B$6,Costos!$G$3:$G$6)*F22)} -> 1680 | J22: =G22*(Costos!$I$2+Costos!$I$3)*24 -> 0 | K22: Proyecto Cúmulo | L22: =IF(K22="Cúmulo VIP",Costos!$I$4,0) -> 0 | N22: =O22+P22 -> 646.4 | O22: {=F22*XLOOKUP(D22,Costos!$B:$B,Costos!$E:$E)} -> 646.4 | P22: =G22*24*Costos!$I$3 -> 0
A23: Maria | B23: 46144.784 | C23: Caja para gafas | D23: ABS | E23: Negro | F23: 35 | G23: 0.10208333 | H23: 0 | I23: {=IF(D23=0,0,XLOOKUP(D23,Costos!$B$3:$B131,Costos!$G$3:$G131)*F23)} -> 7350 | J23: =G23*(Costos!$I$2+Costos!$I$3)*24 -> 2940 | K23: Tercero | L23: =IF(K23="Cúmulo VIP",Costos!$I$4,0) -> 0 | M23: =IF(K23="Proyecto Cúmulo",0,MROUND(SUM(I23:J23)*(1-L23), 100)) -> 10300 | N23: =O23+P23 -> 3318 | O23: {=F23*XLOOKUP(D23,Costos!$B:$B,Costos!$E:$E)} -> 2828 | P23: =G23*24*Costos!$I$3 -> 490 | R23: 8300
A24: Cúmulo | B24: 46147.78 | C24: Gancho secundario celestron | D24: ABS | E24: Negro | F24: 5 | I24: {=IF(D24=0,0,XLOOKUP(D24,Costos!$B$3:$B$6,Costos!$G$3:$G$6)*F24)} -> 1050 | J24: =G24*(Costos!$I$2+Costos!$I$3)*24 -> 0 | K24: Proyecto Cúmulo | L24: =IF(K24="Cúmulo VIP",Costos!$I$4,0) -> 0 | N24: =O24+P24 -> 404 | O24: {=F24*XLOOKUP(D24,Costos!$B:$B,Costos!$E:$E)} -> 404 | P24: =G24*24*Costos!$I$3 -> 0
A25: Jesus Steven Ospina | B25: 46148.743 | C25: Benchy | D25: PLA glow | E25: Verde | F25: 9.28 | G25: 0.025 | H25: 0 | I25: {=IF(D25=0,0,XLOOKUP(D25,Costos!$B$3:$B131,Costos!$G$3:$G131)*F25)} -> 1856 | J25: =G25*(Costos!$I$2+Costos!$I$3)*24 -> 720 | K25: Cúmulo VIP | L25: =IF(K25="Cúmulo VIP",Costos!$I$4,0) -> 0.2 | M25: =IF(K25="Proyecto Cúmulo",0,MROUND(SUM(I25:J25)*(1-L25), 100)) -> 2100 | N25: =O25+P25 -> 1063.4667 | O25: {=F25*XLOOKUP(D25,Costos!$B:$B,Costos!$E:$E)} -> 943.46667 | P25: =G25*24*Costos!$I$3 -> 120
A26: Sara Cortés | B26: 46148.756 | C26: Benchy | D26: PLA glow | E26: Verde | F26: 9.28 | G26: 0.025 | H26: 0 | I26: {=IF(D26=0,0,XLOOKUP(D26,Costos!$B$3:$B131,Costos!$G$3:$G131)*F26)} -> 1856 | J26: =G26*(Costos!$I$2+Costos!$I$3)*24 -> 720 | K26: Cúmulo VIP | L26: =IF(K26="Cúmulo VIP",Costos!$I$4,0) -> 0.2 | M26: =IF(K26="Proyecto Cúmulo",0,MROUND(SUM(I26:J26)*(1-L26), 100)) -> 2100 | N26: =O26+P26 -> 1063.4667 | O26: {=F26*XLOOKUP(D26,Costos!$B:$B,Costos!$E:$E)} -> 943.46667 | P26: =G26*24*Costos!$I$3 -> 120
A27: Cúmulo | B27: 46150.575 | C27: Tapa de linterna | D27: PLA | E27: Negro | F27: 7.24 | I27: {=IF(D27=0,0,XLOOKUP(D27,Costos!$B$3:$B$6,Costos!$G$3:$G$6)*F27)} -> 1303.2 | J27: =G27*(Costos!$I$2+Costos!$I$3)*24 -> 0 | K27: Proyecto Cúmulo | L27: =IF(K27="Cúmulo VIP",Costos!$I$4,0) -> 0 | N27: =O27+P27 -> 621.192 | O27: {=F27*XLOOKUP(D27,Costos!$B:$B,Costos!$E:$E)} -> 621.192 | P27: =G27*24*Costos!$I$3 -> 0
A28: Observatorio | B28: 46161.754 | C28: Prueba tapa enfocador Llinás | D28: PLA | E28: Blanco | F28: 3.5 | I28: {=IF(D28=0,0,XLOOKUP(D28,Costos!$B$3:$B$6,Costos!$G$3:$G$6)*F28)} -> 630 | J28: =G28*(Costos!$I$2+Costos!$I$3)*24 -> 0 | K28: Proyecto Cúmulo | L28: =IF(K28="Cúmulo VIP",Costos!$I$4,0) -> 0 | N28: =O28+P28 -> 300.3 | O28: {=F28*XLOOKUP(D28,Costos!$B:$B,Costos!$E:$E)} -> 300.3 | P28: =G28*24*Costos!$I$3 -> 0
A29: Observatorio | B29: 46163.765 | C29: tapa enfocador llinas | D29: PLA | E29: Negro | F29: 49 | I29: {=IF(D29=0,0,XLOOKUP(D29,Costos!$B$3:$B$6,Costos!$G$3:$G$6)*F29)} -> 8820 | J29: =G29*(Costos!$I$2+Costos!$I$3)*24 -> 0 | K29: Proyecto Cúmulo | L29: =IF(K29="Cúmulo VIP",Costos!$I$4,0) -> 0 | N29: =O29+P29 -> 4204.2 | O29: {=F29*XLOOKUP(D29,Costos!$B:$B,Costos!$E:$E)} -> 4204.2 | P29: =G29*24*Costos!$I$3 -> 0
A30: mesier | B30: 46174.653 | C30: prueba de ajuste espejo 16" | D30: PLA | E30: Negro | F30: 26.4 | I30: {=IF(D30=0,0,XLOOKUP(D30,Costos!$B$3:$B$6,Costos!$G$3:$G$6)*F30)} -> 4752 | J30: =G30*(Costos!$I$2+Costos!$I$3)*24 -> 0 | K30: Proyecto Cúmulo | L30: =IF(K30="Cúmulo VIP",Costos!$I$4,0) -> 0 | N30: =O30+P30 -> 2265.12 | O30: {=F30*XLOOKUP(D30,Costos!$B:$B,Costos!$E:$E)} -> 2265.12 | P30: =G30*24*Costos!$I$3 -> 0
A31: Felipe Muñoz | B31: 46174.761 | C31: funda de celular | D31: PLA | E31: Negro | F31: 31.5 | G31: 0.049305556 | H31: 0 | I31: {=IF(D31=0,0,XLOOKUP(D31,Costos!$B$3:$B131,Costos!$G$3:$G131)*F31)} -> 5670 | J31: =G31*(Costos!$I$2+Costos!$I$3)*24 -> 1420 | K31: Cúmulo VIP | L31: =IF(K31="Cúmulo VIP",Costos!$I$4,0) -> 0.2 | M31: =IF(K31="Proyecto Cúmulo",0,MROUND(SUM(I31:J31)*(1-L31), 100)) -> 5700 | N31: =O31+P31 -> 2939.3667 | O31: {=F31*XLOOKUP(D31,Costos!$B:$B,Costos!$E:$E)} -> 2702.7 | P31: =G31*24*Costos!$I$3 -> 236.66667
A32: amigo de juliana | B32: 46174.83 | C32: dispensador | D32: PLA | E32: Negro | F32: 181.23 | G32: 0.25069444 | H32: 0 | I32: {=IF(D32=0,0,XLOOKUP(D32,Costos!$B$3:$B131,Costos!$G$3:$G131)*F32)} -> 32621.4 | J32: =G32*(Costos!$I$2+Costos!$I$3)*24 -> 7220 | K32: Tercero | L32: =IF(K32="Cúmulo VIP",Costos!$I$4,0) -> 0 | M32: =IF(K32="Proyecto Cúmulo",0,MROUND(SUM(I32:J32)*(1-L32), 100)) -> 39800 | N32: =O32+P32 -> 16752.867 | O32: {=F32*XLOOKUP(D32,Costos!$B:$B,Costos!$E:$E)} -> 15549.534 | P32: =G32*24*Costos!$I$3 -> 1203.3333 | R32: 38600
A34: Cúmulo | B34: 46176.771 | C34: prueba rodamiento | D34: PLA | E34: Negro | F34: 1.7 | I34: {=IF(D34=0,0,XLOOKUP(D34,Costos!$B$3:$B$6,Costos!$G$3:$G$6)*F34)} -> 306 | J34: =G34*(Costos!$I$2+Costos!$I$3)*24 -> 0 | K34: Proyecto Cúmulo | L34: =IF(K34="Cúmulo VIP",Costos!$I$4,0) -> 0 | N34: =O34+P34 -> 145.86 | O34: {=F34*XLOOKUP(D34,Costos!$B:$B,Costos!$E:$E)} -> 145.86 | P34: =G34*24*Costos!$I$3 -> 0
A35: Cúmulo | B35: 46183.775 | C35: cortador de botellas | D35: PLA | E35: Blanco | F35: 14.2 | I35: {=IF(D35=0,0,XLOOKUP(D35,Costos!$B$3:$B131,Costos!$G$3:$G131)*F35)} -> 2556 | J35: =G35*(Costos!$I$2+Costos!$I$3)*24 -> 0 | K35: Proyecto Cúmulo | L35: =IF(K35="Cúmulo VIP",Costos!$I$4,0) -> 0 | M35: =IF(K35="Proyecto Cúmulo",0,MROUND(SUM(I35:J35)*(1-L35), 100)) -> 0 | N35: =O35+P35 -> 1218.36 | O35: {=F35*XLOOKUP(D35,Costos!$B:$B,Costos!$E:$E)} -> 1218.36 | P35: =G35*24*Costos!$I$3 -> 0
A36: Felipe Muñoz | B36: 46185.748 | C36: funda pixel 7 pro | D36: TPE 83a | E36: Negro | F36: 36.18 | G36: 0.10972222 | H36: 0 | I36: {=IF(D36=0,0,XLOOKUP(D36,Costos!$B$3:$B131,Costos!$G$3:$G131)*F36)} -> 8321.4 | J36: =G36*(Costos!$I$2+Costos!$I$3)*24 -> 3160 | K36: Cúmulo VIP | L36: =IF(K36="Cúmulo VIP",Costos!$I$4,0) -> 0.2 | M36: =IF(K36="Proyecto Cúmulo",0,MROUND(SUM(I36:J36)*(1-L36), 100)) -> 9200 | N36: =O36+P36 -> 4535.4107 | O36: {=F36*XLOOKUP(D36,Costos!$B:$B,Costos!$E:$E)} -> 4008.744 | P36: =G36*24*Costos!$I$3 -> 526.66667
A37: Juan Diego Rodríguez | B37: 46191.698 | C37: trofeo mundial | D37: PLA gramos | E37: dorado | F37: 180 | G37: 0.54166667 | H37: 0 | I37: {=IF(D37=0,0,XLOOKUP(D37,Costos!$B$3:$B131,Costos!$G$3:$G131)*F37)} -> 41400 | J37: =G37*(Costos!$I$2+Costos!$I$3)*24 -> 15600 | K37: Cúmulo VIP | L37: =IF(K37="Cúmulo VIP",Costos!$I$4,0) -> 0.2 | M37: =IF(K37="Proyecto Cúmulo",0,MROUND(SUM(I37:J37)*(1-L37), 100)) -> 45600 | N37: =O37+P37 -> 20744 | O37: {=F37*XLOOKUP(D37,Costos!$B:$B,Costos!$E:$E)} -> 18144 | P37: =G37*24*Costos!$I$3 -> 2600
A38: Pedro Urrutia | B38: 46204.57 | C38: benchy | D38: ABS | E38: Gris | F38: 7.8 | G38: 0.024305556 | H38: 0 | I38: {=IF(D38=0,0,XLOOKUP(D38,Costos!$B$3:$B131,Costos!$G$3:$G131)*F38)} -> 1638 | J38: =G38*(Costos!$I$2+Costos!$I$3)*24 -> 700 | K38: Cúmulo VIP | L38: =IF(K38="Cúmulo VIP",Costos!$I$4,0) -> 0.2 | M38: =IF(K38="Proyecto Cúmulo",0,MROUND(SUM(I38:J38)*(1-L38), 100)) -> 1900 | N38: =O38+P38 -> 746.90667 | O38: {=F38*XLOOKUP(D38,Costos!$B:$B,Costos!$E:$E)} -> 630.24 | P38: =G38*24*Costos!$I$3 -> 116.66667

Sheet Costos
B2: material | C2: rollo de 1 kg | D2: boquilla por 1kg | E2: costo por gramo | F2: ganancia por gramo | G2: cobro por gramo | H2: ganancia por hora | I2: 1000 | J2: diseño | K2: costo | L2: extra | O2: modelo de precios
B3: PLA | C3: 85000 | D3: =40000/50 -> 800 | E3: =(C3+D3)/1000 -> 85.8 | F3: =G3-E3 -> 94.2 | G3: 180 | H3: vida útil impresora | I3: 200 | J3: 1 | K3: 1000 | N3: Proyecto | P3: UN | Q3: Proveedor A | R3: Proveedor A | S3: Proveedor A | T3: Proveedor A | U3: Proveedor A | V3: Proveedor A | W3: Proveedor A | X3: Cúmulo
B4: PLA glow | C4: 95000 | D4: =40000/6 -> 6666.6667 | E4: =(C4+D4)/1000 -> 101.66667 | F4: =G4-E4 -> 98.333333 | G4: 200 | H4: descuento VIP | I4: 0.2 | J4: 2 | K4: 5000 | N4: araña | P4: cobro de 350 por gramo únicamente
B5: ABS | C5: 80000 | D5: =40000/50 -> 800 | E5: =(C5+D5)/1000 -> 80.8 | F5: =G5-E5 -> 129.2 | G5: 210 | J5: 3
B6: TPU 95a | C6: 90000 | D6: =40000/50 -> 800 | E6: =(C6+D6)/1000 -> 90.8 | F6: =G6-E6 -> 109.2 | G6: 200 | J6: 4
B7: PLA gramos | C7: 100000 | D7: =40000/50 -> 800 | E7: =(C7+D7)/1000 -> 100.8 | F7: =G7-E7 -> 129.2 | G7: 230 | J7: 5
B8: TPE 83a | C8: 110000 | D8: =40000/50 -> 800 | E8: =(C8+D8)/1000 -> 110.8 | F8: =G8-E8 -> 119.2 | G8: 230

Sheet Astrochaza
A1: Elemento | B1: Costo | C1: Precio
A2: Estrella pequeña | B2: 70 | C2: 111.475
A3: Luna grande | B3: 506 | C3: 805.805
A4: Saturno | B4: 201 | C4: 320.0925
A5: Cometa grande | B5: 268 | C5: 426.79
A6: Estrella grande | B6: 394 | C6: 627.445
A7: Cometa mediano | B7: 158 | C7: 251.615
A8: Cometa pequeño | B8: 186 | C8: 296.205
A9: Luna pequeña | B9: 117 | C9: 186.3225
A10: Astronauta grande | B10: 2284 | C10: 3000
A11: Astronauta pequeño | B11: 511 | C11: 1000
A13: Paquete grande | B13: =SUM(B14:B21) -> 22 | C13: =SUM(C14:C21) -> 2880 | D13: =SUM(D14:D21) -> 4586.4 | F13: Paquete pequeño | G13: =SUM(G14:G21) -> 26 | H13: =SUM(H14:H21) -> 1867 | I13: =SUM(I14:I21) -> 2973.1975
A14: Estrella pequeña | B14: 15 | C14: =B14*B2 -> 1050 | D14: =B14*C2 -> 1672.125 | F14: Estrella pequeña | G14: 25 | H14: =G14*B2 -> 1750 | I14: =G14*C2 -> 2786.875
A15: Luna grande | B15: 1 | C15: =B15*B3 -> 506 | D15: =B15*C3 -> 805.805 | F15: Luna grande | G15: 0 | H15: =G15*B3 -> 0 | I15: =G15*C3 -> 0
A16: Saturno | B16: 1 | C16: =B16*B4 -> 201 | D16: =B16*C4 -> 320.0925 | F16: Saturno | G16: 0 | H16: =G16*B4 -> 0 | I16: =G16*C4 -> 0
A17: Cometa grande | B17: 1 | C17: =B17*B5 -> 268 | D17: =B17*C5 -> 426.79 | F17: Cometa grande | G17: 0 | H17: =G17*B5 -> 0 | I17: =G17*C5 -> 0
A18: Estrella grande | B18: 1 | C18: =B18*B6 -> 394 | D18: =B18*C6 -> 627.445 | F18: Estrella grande | G18: 0 | H18: =G18*B6 -> 0 | I18: =G18*C6 -> 0
A19: Cometa mediano | B19: 1 | C19: =B19*B7 -> 158 | D19: =B19*C7 -> 251.615 | F19: Cometa mediano | G19: 0 | H19: =G19*B7 -> 0 | I19: =G19*C7 -> 0
A20: Cometa pequeño | B20: 1 | C20: =B20*B8 -> 186 | D20: =B20*C8 -> 296.205 | F20: Cometa pequeño | G20: 0 | H20: =G20*B8 -> 0 | I20: =G20*C8 -> 0
A21: Luna pequeña | B21: 1 | C21: =B21*B9 -> 117 | D21: =B21*C9 -> 186.3225 | F21: Luna pequeña | G21: 1 | H21: =G21*B9 -> 117 | I21: =G21*C9 -> 186.3225
A23: Producto Cúmulo | B23: Precio | C23: Cantidad
A24: Paquete grande | B24: 8000 | C24: 1
A25: Paquete pequeño | B25: 4000 | C25: 5
A26: Astronauta grande | B26: 5000 | C26: 1
A27: Astronauta pequeño | B27: 3000

Sheet VIP
A1: VIP | B1: Impresiones
A2: Daniel Felipe Garnica
A3: Diego Bernal
A4: Edward Velasco
A5: Felipe Muñoz
A6: Hernán David Munar
A7: Islena
A8: Jesus Steven Ospina
A9: Johann Sánchez
A10: Joseph Alejandro Niño
A11: Juan Diego Rodríguez
A12: Juan Pablo Garavito
A13: Julián David Acosta
... A32: Astrochaza

Sheet Inventario

Sheet inventario (operaciones)
A1: Filamento | B1: Color | C1: cantidad | D1: operacion
A2: ABS | B2: Negro | D2: inventariado
A3: ABS | B3: Gris | D3: inventariado
A4: ABS | B4: Naranja | D4: inventariado
A5: PLA | B5: Blanco | D5: inventariado
A6: PLA | B6: Negro | D6: inventariado
A7: PLA glow | B7: Verde | D7: inventariado
A8: TPU 95a | B8: Translúcido | D8: inventariado
